sibyl_core/__init__.py
sibyl_core/_version.py
sibyl_core/config.py
sibyl_core/errors.py
sibyl_core/auth/__init__.py
sibyl_core/auth/context.py
sibyl_core/auth/jwt.py
sibyl_core/auth/passwords.py
sibyl_core/graph/__init__.py
sibyl_core/graph/batch.py
sibyl_core/graph/client.py
sibyl_core/graph/communities.py
sibyl_core/graph/entities.py
sibyl_core/graph/mock_llm.py
sibyl_core/graph/relationships.py
sibyl_core/graph/search_interface.py
sibyl_core/graph/summarize.py
sibyl_core/logging/__init__.py
sibyl_core/logging/colors.py
sibyl_core/logging/config.py
sibyl_core/logging/formatters.py
sibyl_core/models/__init__.py
sibyl_core/models/agents.py
sibyl_core/models/entities.py
sibyl_core/models/projects.py
sibyl_core/models/responses.py
sibyl_core/models/sources.py
sibyl_core/models/tasks.py
sibyl_core/models/tools.py
sibyl_core/retrieval/__init__.py
sibyl_core/retrieval/bm25.py
sibyl_core/retrieval/dedup.py
sibyl_core/retrieval/fusion.py
sibyl_core/retrieval/hybrid.py
sibyl_core/retrieval/reranking.py
sibyl_core/retrieval/temporal.py
sibyl_core/tasks/__init__.py
sibyl_core/tasks/dependencies.py
sibyl_core/tasks/estimation.py
sibyl_core/tasks/manager.py
sibyl_core/tasks/workflow.py
sibyl_core/tools/__init__.py
sibyl_core/tools/add.py
sibyl_core/tools/admin.py
sibyl_core/tools/conflicts.py
sibyl_core/tools/core.py
sibyl_core/tools/explore.py
sibyl_core/tools/health.py
sibyl_core/tools/helpers.py
sibyl_core/tools/manage.py
sibyl_core/tools/responses.py
sibyl_core/tools/search.py
sibyl_core/tools/temporal.py
sibyl_core/utils/__init__.py
sibyl_core/utils/metadata.py
sibyl_core/utils/resilience.py
sibyl_core-0.2.3.dist-info/METADATA
sibyl_core-0.2.3.dist-info/WHEEL
sibyl_core-0.2.3.dist-info/RECORD
