Metadata-Version: 2.4
Name: sibyl-core
Version: 0.2.3
Summary: Core library for Sibyl - domain models, graph operations, and knowledge retrieval
Project-URL: Homepage, https://github.com/hyperb1iss/sibyl
Project-URL: Repository, https://github.com/hyperb1iss/sibyl
Author-email: Stefanie Jane <stef@hyperbliss.tech>
License-Expression: Apache-2.0
Keywords: ai-agents,collective-intelligence,graph-rag,knowledge-graph
Classifier: Development Status :: 3 - Alpha
Classifier: Intended Audience :: Developers
Classifier: License :: OSI Approved :: Apache Software License
Classifier: Programming Language :: Python :: 3
Classifier: Programming Language :: Python :: 3.13
Classifier: Typing :: Typed
Requires-Python: >=3.13
Requires-Dist: anyio>=4.0
Requires-Dist: crawl4ai>=0.7.8
Requires-Dist: graphiti-core[anthropic,falkordb]>=0.24
Requires-Dist: httpx>=0.27
Requires-Dist: mistune>=3.0
Requires-Dist: passlib>=1.7
Requires-Dist: pydantic-settings>=2.0
Requires-Dist: pydantic>=2.0
Requires-Dist: pyjwt>=2.10
Requires-Dist: python-dotenv>=1.0
Requires-Dist: python-louvain>=0.16
Requires-Dist: structlog>=24.0
